{
  "phase": "telegram_mt5_bot_informational_v1",
  "method_version": "telegram_mt5_bot_informational_v1",
  "created_at_utc": "2026-06-11T15:10:07Z",
  "decision": "telegram_mt5_bot_informational_v1_ready_for_sender_gate_alignment",
  "telegram_mt5_bot_informational_implemented": true,
  "dry_run_only": true,
  "fixture_mode": true,
  "manual_preview": false,
  "telegram_connected": false,
  "telegram_messages_sent": 0,
  "telegram_real_messages_sent": 0,
  "telegram_command_bot_implemented": false,
  "telegram_can_confirm": false,
  "telegram_can_trade": false,
  "telegram_confirms_orders": false,
  "telegram_modifies_positions": false,
  "telegram_tokens_read": false,
  "telegram_tokens_printed": false,
  "telegram_tokens_stored": false,
  "telegram_chat_ids_read": false,
  "telegram_chat_ids_printed": false,
  "telegram_chat_ids_stored": false,
  "mt5_connected": false,
  "orders_sent": 0,
  "mt5_orders_sent": 0,
  "sql_real_written": false,
  "ddl_executed": false,
  "backtests_executed": false,
  "messages_rendered_count": 8,
  "messages_preview_allowed_count": 7,
  "messages_blocked_count": 0,
  "message_types_rendered": [
    "daily_summary",
    "demo_order_event_notice",
    "demo_position_close_notice",
    "mt5_account_snapshot_notice",
    "mt5_bot_status_digest",
    "mt5_positions_digest",
    "refresh_pipeline_notice",
    "riskguard_block_notice"
  ]
}
